django_perm_filter/__init__.py
django_perm_filter/admin.py
django_perm_filter/apps.py
django_perm_filter/mixins.py
django_perm_filter/models.py
django_perm_filter/settings.py
django_perm_filter/utils.py
django_perm_filter-0.2.4.dist-info/AUTHORS.md
django_perm_filter-0.2.4.dist-info/LICENSE
django_perm_filter-0.2.4.dist-info/METADATA
django_perm_filter-0.2.4.dist-info/WHEEL
django_perm_filter-0.2.4.dist-info/top_level.txt
django_perm_filter-0.2.4.dist-info/RECORD
