Metadata-Version: 2.1
Name: django-perm-filter
Version: 0.2.4
Summary: A simple app that can be included in Django projects which hides app specific permissions from any type of User.
Author-email: Tim Santor <tsantor@xstudios.com>
Project-URL: Repository, https://github.com/tsantor/django-perm-filter.git
Project-URL: Issues, https://github.com/tsantor/django-perm-filter/issues
Project-URL: Changelog, https://github.com/tsantor/django-perm-filter/blob/master/HISTORY.md
Classifier: Development Status :: 5 - Production/Stable
Classifier: Environment :: Console
Classifier: Intended Audience :: Developers
Classifier: Natural Language :: English
Classifier: Programming Language :: Python :: 3.10
Classifier: Programming Language :: Python :: 3.11
Classifier: Programming Language :: Python :: 3.12
Requires-Python: >=3.9
License-File: LICENSE
License-File: AUTHORS.md
Requires-Dist: django <5.0,>=4.0
Provides-Extra: dev
